skill_ovos_fallback_chatgpt/LICENSE
skill_ovos_fallback_chatgpt/MANIFEST.in
skill_ovos_fallback_chatgpt/README.md
skill_ovos_fallback_chatgpt/__init__.py
skill_ovos_fallback_chatgpt/version.py
skill_ovos_fallback_chatgpt/locale/ca-es/asking.dialog
skill_ovos_fallback_chatgpt/locale/ca-es/gpt_error.dialog
skill_ovos_fallback_chatgpt/locale/ca-es/skill.json
skill_ovos_fallback_chatgpt/locale/da-dk/asking.dialog
skill_ovos_fallback_chatgpt/locale/da-dk/gpt_error.dialog
skill_ovos_fallback_chatgpt/locale/da-dk/skill.json
skill_ovos_fallback_chatgpt/locale/de-de/asking.dialog
skill_ovos_fallback_chatgpt/locale/de-de/gpt_error.dialog
skill_ovos_fallback_chatgpt/locale/de-de/skill.json
skill_ovos_fallback_chatgpt/locale/en-us/asking.dialog
skill_ovos_fallback_chatgpt/locale/en-us/gpt_error.dialog
skill_ovos_fallback_chatgpt/locale/en-us/skill.json
skill_ovos_fallback_chatgpt/locale/eu/asking.dialog
skill_ovos_fallback_chatgpt/locale/eu/gpt_error.dialog
skill_ovos_fallback_chatgpt/locale/fr-fr/asking.dialog
skill_ovos_fallback_chatgpt/locale/fr-fr/gpt_error.dialog
skill_ovos_fallback_chatgpt/locale/gl-es/asking.dialog
skill_ovos_fallback_chatgpt/locale/gl-es/gpt_error.dialog
skill_ovos_fallback_chatgpt/locale/it-it/asking.dialog
skill_ovos_fallback_chatgpt/locale/it-it/gpt_error.dialog
skill_ovos_fallback_chatgpt/locale/it-it/skill.json
skill_ovos_fallback_chatgpt/locale/nl-nl/asking.dialog
skill_ovos_fallback_chatgpt/locale/nl-nl/gpt_error.dialog
skill_ovos_fallback_chatgpt/locale/pt-pt/asking.dialog
skill_ovos_fallback_chatgpt/locale/pt-pt/gpt_error.dialog
skill_ovos_fallback_chatgpt/locale/pt-pt/skill.json
skill_ovos_fallback_chatgpt/skill_ovos_fallback_chatgpt.egg-info/PKG-INFO
skill_ovos_fallback_chatgpt/skill_ovos_fallback_chatgpt.egg-info/SOURCES.txt
skill_ovos_fallback_chatgpt/skill_ovos_fallback_chatgpt.egg-info/dependency_links.txt
skill_ovos_fallback_chatgpt/skill_ovos_fallback_chatgpt.egg-info/entry_points.txt
skill_ovos_fallback_chatgpt/skill_ovos_fallback_chatgpt.egg-info/requires.txt
skill_ovos_fallback_chatgpt/skill_ovos_fallback_chatgpt.egg-info/top_level.txt
skill_ovos_fallback_chatgpt-0.1.13.dist-info/LICENSE
skill_ovos_fallback_chatgpt-0.1.13.dist-info/METADATA
skill_ovos_fallback_chatgpt-0.1.13.dist-info/WHEEL
skill_ovos_fallback_chatgpt-0.1.13.dist-info/entry_points.txt
skill_ovos_fallback_chatgpt-0.1.13.dist-info/top_level.txt
skill_ovos_fallback_chatgpt-0.1.13.dist-info/RECORD
