Metadata-Version: 2.1
Name: skill-ovos-fallback-chatgpt
Version: 0.1.13
Summary: ovos chatGPT skill
Home-page: https://github.com/OpenVoiceOS/skill-ovos-fallback-chatgpt
Author: JarbasAi
Author-email: jarbasai@mailfence.com
License: Apache-2.0
Keywords: ovos skill plugin
License-File: LICENSE
Requires-Dist: ovos-solver-openai-persona-plugin>=0.0.0a8
Requires-Dist: ovos-utils>=0.0.38
Requires-Dist: ovos-workshop<4.0.0,>=0.0.15
Requires-Dist: ovos-plugin-manager<1.0.0,>=0.0.26
Requires-Dist: ovos-translate-server-plugin
